hitgpa/__init__.py
hitgpa/__main__.py
hitgpa/entry.py
hitgpa-0.2.0.dist-info/LICENSE
hitgpa-0.2.0.dist-info/METADATA
hitgpa-0.2.0.dist-info/WHEEL
hitgpa-0.2.0.dist-info/entry_points.txt
hitgpa-0.2.0.dist-info/top_level.txt
hitgpa-0.2.0.dist-info/RECORD
