Metadata-Version: 2.1
Name: hitgpa
Version: 0.2.0
Summary: Query data from jwes and calculate GPA in many kinds of arithmetics
Home-page: https://github.com/inclyc/HIT-GPA-Converter
Author: inclyc
Author-email: axoford@icloud.com
License: UNKNOWN
Project-URL: Bug Reports, https://github.com/inclyc/HIT-GPA-Converter/issues
Project-URL: Source, https://github.com/inclyc/HIT-GPA-Converter
Keywords: Harbin Institute of Technology,HIT,GPA
Platform: UNKNOWN
Classifier: Development Status :: 2 - Pre-Alpha
Classifier: Intended Audience :: Developers
Classifier: License :: OSI Approved :: GNU Affero General Public License v3 or later (AGPLv3+)
Classifier: Natural Language :: Chinese (Simplified)
Classifier: Natural Language :: English
Classifier: Operating System :: MacOS
Classifier: Operating System :: Microsoft :: Windows
Classifier: Operating System :: POSIX :: Linux
Classifier: Programming Language :: Python :: 3
Classifier: Programming Language :: Python :: 3.7
Classifier: Programming Language :: Python :: 3.8
Classifier: Programming Language :: Python :: 3 :: Only
Classifier: Topic :: Utilities
Requires-Python: >=3.5, <4
Requires-Dist: gpalib
Requires-Dist: hitutil-en
Requires-Dist: lxml
Requires-Dist: pandas
